ruffrgimportfixer/README.MD
ruffrgimportfixer/__init__.py
ruffrgimportfixer/requirements.txt
ruffrgimportfixer/thirdparty.json
ruffrgimportfixer-0.11.dist-info/LICENSE.rst
ruffrgimportfixer-0.11.dist-info/METADATA
ruffrgimportfixer-0.11.dist-info/WHEEL
ruffrgimportfixer-0.11.dist-info/top_level.txt
ruffrgimportfixer-0.11.dist-info/RECORD
