Metadata-Version: 2.1
Name: ruffrgimportfixer
Version: 0.11
Summary: Fixes missing imports using Ruff and RipGrep (CLI and import)
Home-page: https://github.com/hansalemaos/ruffrgimportfixer
Author: Johannes Fischer
Author-email: aulasparticularesdealemaosp@gmail.com
License: MIT
Keywords: import,ripgrep,ruff
Classifier: Development Status :: 4 - Beta
Classifier: Programming Language :: Python :: 3 :: Only
Classifier: Programming Language :: Python :: 3.10
Classifier: Topic :: Software Development :: Libraries :: Python Modules
Classifier: Topic :: Utilities
License-File: LICENSE.rst
